django_freezer/__init__.py
django_freezer/admin.py
django_freezer/models.py
django_freezer/test_settings.py
django_freezer/tests.py
django_freezer/views.py
django_freezer/static/django_freezer/css/admin_freezer.css
django_freezer/templates/django_freezer/index.html
django_freezer-0.1.4.dist-info/top_level.txt
django_freezer-0.1.4.dist-info/METADATA
django_freezer-0.1.4.dist-info/DESCRIPTION.rst
django_freezer-0.1.4.dist-info/metadata.json
django_freezer-0.1.4.dist-info/WHEEL
django_freezer-0.1.4.dist-info/RECORD
